{"is_source_file": true, "format": "JavaScript (React)", "description": "This is the main entry point for a React web application, responsible for rendering the root component into the DOM.", "external_files": ["./index.css", "./App"], "external_methods": ["ReactDOM.createRoot", "root.render"], "published": [], "classes": [], "methods": [{"name": "ReactDOM.createRoot", "description": "Creates a root React node for rendering the application."}, {"name": "root.render", "description": "Renders the React element into the DOM."}], "calls": ["ReactDOM.createRoot", "root.render"], "search-terms": ["React", "ReactDOM", "index.js", "entry point", "render", "DOM", "main component"], "state": 2, "file_id": 2, "knowledge_revision": 24, "git_revision": "87f4025d8846a04b5414192717c4747416b10edf", "ctags": [{"_type": "tag", "name": "root", "path": "/home/kavia/workspace/code-generation/sudoku-mastermind-331600-331615/frontend_app/src/index.js", "pattern": "/^const root = ReactDOM.createRoot(document.getElementById('root'));$/", "language": "JavaScript", "kind": "constant"}], "hash": "9fc5841375336fc175b49f8767a11383", "format-version": 4, "code-base-name": "frontend_app", "filename": "frontend_app/src/index.js", "revision_history": [{"24": "87f4025d8846a04b5414192717c4747416b10edf"}]}